flake8_no_nesting.py
flake8_no_nesting-0.1.2.dist-info/METADATA
flake8_no_nesting-0.1.2.dist-info/WHEEL
flake8_no_nesting-0.1.2.dist-info/entry_points.txt
flake8_no_nesting-0.1.2.dist-info/top_level.txt
flake8_no_nesting-0.1.2.dist-info/RECORD
